ecoml/__init__.py
ecoml/dashboard.py
ecoml/enable.py
ecoml/gemini_helper.py
ecoml/hardware_monitor.py
ecoml/metrics.py
ecoml/predictor.py
ecoml/recommender.py
ecoml/tracker.py
ecoml/ui.py
ecoml/utils.py
ecoml-0.1.3.dist-info/METADATA
ecoml-0.1.3.dist-info/WHEEL
ecoml-0.1.3.dist-info/top_level.txt
ecoml-0.1.3.dist-info/RECORD
